autosec/__init__.py
autosec/cli.py
autosec/agent/__init__.py
autosec/agent/graph.py
autosec/agent/llm.py
autosec/agent/state.py
autosec/agent/nodes/__init__.py
autosec/agent/nodes/coder.py
autosec/agent/nodes/planner.py
autosec/agent/nodes/reflector.py
autosec/execution/__init__.py
autosec/execution/sandbox_runner.py
autosec/ingestion/__init__.py
autosec/ingestion/nvd_ingest.py
autosec/tests/__init__.py
autosec/tests/test_cst.py
autosec/tests/test_graph.py
autosec/tests/test_lab_rat.py
autosec/tools/__init__.py
autosec/tools/code_editor.py
autosec/tools/cst_transformer.py
autosec/ui/__init__.py
autosec/ui/app.py
sentinel_sec-0.1.6.dist-info/licenses/LICENSE
sentinel_sec-0.1.6.dist-info/METADATA
sentinel_sec-0.1.6.dist-info/WHEEL
sentinel_sec-0.1.6.dist-info/entry_points.txt
sentinel_sec-0.1.6.dist-info/top_level.txt
sentinel_sec-0.1.6.dist-info/RECORD
