Metadata-Version: 2.4
Name: sentinel-sec
Version: 0.1.6
Summary: 🛡️ Autonomous Security Agent that finds AND fixes vulnerabilities in your code.
Home-page: https://github.com/YOUR_USERNAME/project-sentinel
Author: Project Sentinel Team
Author-email: sentinel@example.com
Project-URL: Bug Tracker, https://github.com/YOUR_USERNAME/project-sentinel/issues
Project-URL: Documentation, https://github.com/YOUR_USERNAME/project-sentinel#readme
Project-URL: Source Code, https://github.com/YOUR_USERNAME/project-sentinel
Keywords: security,vulnerability,ai,llm,code-fix,sast,devsecops,llama,groq
Classifier: Development Status :: 4 - Beta
Classifier: Intended Audience :: Developers
Classifier: Topic :: Security
Classifier: Topic :: Software Development :: Quality Assurance
Classifier: License :: OSI Approved :: MIT License
Classifier: Programming Language :: Python :: 3
Classifier: Programming Language :: Python :: 3.12
Classifier: Operating System :: OS Independent
Requires-Python: >=3.10
License-File: LICENSE
Requires-Dist: langgraph
Requires-Dist: langchain
Requires-Dist: langchain-groq
Requires-Dist: langchain-openai
Requires-Dist: chromadb
Requires-Dist: libcst
Requires-Dist: pydantic
Requires-Dist: qdrant-client
Requires-Dist: docker
Requires-Dist: coloredlogs
Requires-Dist: chainlit
Requires-Dist: python-dotenv
Dynamic: author
Dynamic: author-email
Dynamic: classifier
Dynamic: description
Dynamic: description-content-type
Dynamic: home-page
Dynamic: keywords
Dynamic: license-file
Dynamic: project-url
Dynamic: requires-dist
Dynamic: requires-python
Dynamic: summary
